peupasswd/__init__.py
peupasswd/pencryptor.py
peupasswd/views.py
peupasswd-1.0.1.2.dist-info/METADATA
peupasswd-1.0.1.2.dist-info/WHEEL
peupasswd-1.0.1.2.dist-info/top_level.txt
peupasswd-1.0.1.2.dist-info/RECORD
