Metadata-Version: 2.1
Name: peupasswd
Version: 1.0.1.2
Summary: A password security software
Author: blackstackhub (Black Stack Hub)
Author-email: <blackstackhub@gmail.com>
Keywords: peupasswd,security,password security,neupasswd,encryption
Classifier: Development Status :: 1 - Planning
Classifier: Intended Audience :: Developers
Classifier: Programming Language :: Python :: 3
Classifier: Operating System :: Unix
Classifier: Operating System :: MacOS :: MacOS X
Classifier: Operating System :: Microsoft :: Windows
